{"book_id":3,"chapter_id":19,"links":[{"verse_id":2,"content":"1Петр 1:15; Лев 11:44"},{"verse_id":3,"content":"Исх 20:12, 8"},{"verse_id":4,"content":"Исх 20:4"},{"verse_id":5,"content":"Лев 3:1"},{"verse_id":6,"content":"Лев 7:16"},{"verse_id":7,"content":"Лев 7:18"},{"verse_id":8,"content":"Быт 17:14"},{"verse_id":9,"content":"Втор 24:19; Лев 23:22"},{"verse_id":11,"content":"Исх 20:15"},{"verse_id":12,"content":"Втор 5:11; Исх 20:7; Мф 5:33"},{"verse_id":13,"content":"Втор 24:14"},{"verse_id":15,"content":"Втор 1:17; 16:19; Иак 2:1; Прит 24:23"},{"verse_id":17,"content":"1Ин 2:11; 3:15; Лк 17:3; Мф 18:15"},{"verse_id":18,"content":"Гал 5:14; Иак 2:8; Мф 5:43; 22:39; Мк 12:31; Рим 13:9"},{"verse_id":22,"content":"Лев 4:26; 5:13"},{"verse_id":23,"content":"Втор 20:6"},{"verse_id":24,"content":"Неем 10:35"},{"verse_id":26,"content":"4Цар 21:6; Втор 18:10"},{"verse_id":28,"content":"3Цар 18:28; Втор 14:1"},{"verse_id":30,"content":"Лев 23:2"},{"verse_id":31,"content":"Втор 18:11; Ис 8:19; Лев 20:6"},{"verse_id":33,"content":"Исх 22:21"},{"verse_id":36,"content":"Втор 25:13; Иез 45:10; Прит 11:1"},{"verse_id":37,"content":"Втор 7:12; Лев 18:30"}]}