{"book_id":46,"chapter_id":5,"links":[{"verse_id":1,"content":"Деян 1:8; Рим 8:17"},{"verse_id":2,"content":"Деян 20:28"},{"verse_id":3,"content":"Мк 10:44"},{"verse_id":4,"content":"1Кор 9:25; 1Петр 2:25"},{"verse_id":5,"content":"Еф 5:21; Иак 4:6; Фил 2:3"},{"verse_id":6,"content":"Иак 4:10"},{"verse_id":7,"content":"Лк 12:30; Мф 6:32; Пс 54:23"},{"verse_id":8,"content":"Иов 1:7; 2:2; Лк 22:31"},{"verse_id":9,"content":"Деян 14:22"},{"verse_id":10,"content":"2Кор 4:17"},{"verse_id":14,"content":"1Кор 16:20; 2Кор 13:12; Рим 16:16"}]}