{"book_id":4,"chapter_id":32,"links":[{"verse_id":1,"content":"Быт 46:32; 47:3"},{"verse_id":7,"content":"Деян 21:13; Втор 1:28"},{"verse_id":8,"content":"Чис 13:3"},{"verse_id":9,"content":"Втор 1:28; Чис 13:24, 32"},{"verse_id":10,"content":"Чис 14:28; 26:65"},{"verse_id":11,"content":"Быт 50:24; Чис 14:23"},{"verse_id":12,"content":"Чис 14:30"},{"verse_id":17,"content":"Втор 3:18"},{"verse_id":18,"content":"Нав 22:1"},{"verse_id":19,"content":"Втор 3:12"},{"verse_id":20,"content":"Нав 1:13"},{"verse_id":24,"content":"Втор 23:23"},{"verse_id":29,"content":"Нав 4:12"},{"verse_id":33,"content":"Втор 3:12; Нав 13:8"},{"verse_id":39,"content":"Быт 50:23"},{"verse_id":41,"content":"1Пар 2:22; Нав 13:30"},{"verse_id":42,"content":"1Пар 2:23; Суд 8:11; Чис 21:25"}]}