{"book_id":20,"chapter_id":15,"links":[{"verse_id":1,"content":"1Цар 25:24, 35; Прит 15:28"},{"verse_id":2,"content":"Прит 12:23"},{"verse_id":3,"content":"Евр 4:13; Пс 32:14"},{"verse_id":4,"content":"Прит 3:18; 11:30; 12:18"},{"verse_id":6,"content":"Иов 20:22; Пс 111:3"},{"verse_id":8,"content":"Ам 5:21; Ис 1:11; Иер 6:20; Прит 21:27"},{"verse_id":9,"content":"Пс 5:7"},{"verse_id":11,"content":"Иов 26:6; Пс 7:10"},{"verse_id":13,"content":"Прит 17:22"},{"verse_id":15,"content":"Еккл 3:12"},{"verse_id":16,"content":"Пс 36:16"},{"verse_id":17,"content":"Прит 17:1"},{"verse_id":18,"content":"Прит 26:21"},{"verse_id":19,"content":"1Ин 2:10"},{"verse_id":20,"content":"Прит 10:1; 17:25; 19:13, 26"},{"verse_id":22,"content":"Прит 11:14; 20:18"},{"verse_id":25,"content":"Есф 7:9; Прит 2:22; 12:7"},{"verse_id":27,"content":"1Тим 6:9; Исх 23:8"},{"verse_id":29,"content":"Ис 1:15; Иак 5:16; Пс 10:5"}]}