{"book_id":26,"chapter_id":36,"links":[{"verse_id":1,"content":"Иез 6:2"},{"verse_id":2,"content":"Иез 25:3; 26:2; Авд 1:12"},{"verse_id":6,"content":"Иез 39:25; Иоил 2:18"},{"verse_id":8,"content":"Иер 31:4"},{"verse_id":9,"content":"Зах 8:12; 10:8"},{"verse_id":11,"content":"Втор 30:3, 5"},{"verse_id":13,"content":"Лев 26:38"},{"verse_id":15,"content":"Ис 25:8"},{"verse_id":17,"content":"Ис 64:6"},{"verse_id":19,"content":"Иез 20:23; 22:15"},{"verse_id":20,"content":"Ис 52:5; Рим 2:24"},{"verse_id":21,"content":"Чис 14:15"},{"verse_id":22,"content":"Втор 9:6; Иез 36:32"},{"verse_id":23,"content":"Иез 39:27; Мф 6:9; Рим 2:24"},{"verse_id":25,"content":"Ис 44:3; Зах 13:1"},{"verse_id":26,"content":"Деян 2:17; Иез 11:19; Иер 32:39; Иоил 2:28"},{"verse_id":27,"content":"Ис 59:21"},{"verse_id":28,"content":"Иез 11:20; 37:23"},{"verse_id":29,"content":"Ос 2:21; Пс 31:2; Зах 9:17"},{"verse_id":31,"content":"Иез 6:9; 16:61"},{"verse_id":32,"content":"Иез 36:22"},{"verse_id":35,"content":"Ис 51:3"},{"verse_id":36,"content":"Иез 17:24"},{"verse_id":38,"content":"Мих 2:12"}]}