{"book_id":43,"chapter_id":6,"links":[{"verse_id":4,"content":"Исх 12:18"},{"verse_id":5,"content":"Лк 9:12; Мф 14:16; Мк 6:35"},{"verse_id":13,"content":"Мк 8:19"},{"verse_id":14,"content":"Втор 18:15; Мф 11:3"},{"verse_id":17,"content":"Мф 14:22; Мк 6:47"},{"verse_id":27,"content":"Ин 1:32; 10:36; Мф 3:17"},{"verse_id":29,"content":"1Ин 3:23; Ин 17:3"},{"verse_id":31,"content":"1Кор 10:3; Исх 16:14; Чис 11:7; Пс 77:24"},{"verse_id":35,"content":"Ин 4:14; 7:37"},{"verse_id":38,"content":"Ин 8:29; Мф 26:39"},{"verse_id":39,"content":"Ин 10:28"},{"verse_id":42,"content":"Мф 13:55"},{"verse_id":45,"content":"Ис 54:13; Иер 31:34"},{"verse_id":46,"content":"Мф 11:27"},{"verse_id":49,"content":"Ин 6:31"},{"verse_id":53,"content":"Мф 26:26"},{"verse_id":62,"content":"Еф 4:8; Ин 3:13; Мф 26:64"},{"verse_id":63,"content":"2Кор 3:6; Рим 8:2"},{"verse_id":64,"content":"Ин 2:24; Мк 2:8"},{"verse_id":65,"content":"Ин 3:27"},{"verse_id":69,"content":"Лк 9:20; Мф 16:16; Мк 8:29"},{"verse_id":70,"content":"Лк 6:13"}]}