{"book_id":40,"chapter_id":10,"links":[{"verse_id":1,"content":"Лк 9:1; Мк 3:14"},{"verse_id":6,"content":"Мф 15:24"},{"verse_id":7,"content":"Лк 9:2"},{"verse_id":9,"content":"Лк 9:3; Мк 6:8"},{"verse_id":10,"content":"1Тим 5:18; Лк 10:7"},{"verse_id":12,"content":"Лк 10:5"},{"verse_id":14,"content":"Деян 13:51; Лк 9:5; Мк 6:11"},{"verse_id":16,"content":"2Кор 1:12; Лк 10:3; Рим 16:19"},{"verse_id":19,"content":"Лк 12:11; Мк 13:11"},{"verse_id":24,"content":"Ин 13:16; 15:20; Лк 6:40"},{"verse_id":25,"content":"Мф 9:34"},{"verse_id":26,"content":"Лк 8:17; 12:2; Мк 4:22"},{"verse_id":28,"content":"Лк 12:4"},{"verse_id":29,"content":"Лк 12:6"},{"verse_id":32,"content":"Лк 9:26; 12:8; Мк 8:38"},{"verse_id":33,"content":"2Тим 2:12"},{"verse_id":34,"content":"Лк 12:51"},{"verse_id":36,"content":"Мих 7:6"},{"verse_id":37,"content":"Лк 14:26"},{"verse_id":38,"content":"Мф 16:24; Мк 8:34"},{"verse_id":39,"content":"Ин 12:25; Лк 9:24; Мк 8:35"},{"verse_id":40,"content":"Ин 13:20; Лк 10:16"},{"verse_id":42,"content":"Мк 9:41"}]}