{"book_id":24,"chapter_id":27,"links":[{"verse_id":2,"content":"2Пар 10:4; Наум 1:13"},{"verse_id":3,"content":"Иер 48:1"},{"verse_id":5,"content":"Дан 4:22"},{"verse_id":6,"content":"Иер 25:9; 28:14"},{"verse_id":7,"content":"Иер 25:14"},{"verse_id":9,"content":"Иер 23:16"},{"verse_id":13,"content":"Иез 18:32"},{"verse_id":15,"content":"Иер 14:14; 23:21"},{"verse_id":16,"content":"Иер 28:3"},{"verse_id":19,"content":"4Цар 25:13; Иер 52:17"},{"verse_id":20,"content":"4Цар 24:12"},{"verse_id":22,"content":"2Пар 36:18, 22; 4Цар 25:13"}]}